paylands/__init__.py
paylands/client.py
paylands/exceptions.py
paylands/session.py
paylands/version.py
paylands-0.0.1.dist-info/LICENSE
paylands-0.0.1.dist-info/METADATA
paylands-0.0.1.dist-info/WHEEL
paylands-0.0.1.dist-info/top_level.txt
paylands-0.0.1.dist-info/zip-safe
paylands-0.0.1.dist-info/RECORD
