Metadata-Version: 2.1
Name: paylands
Version: 0.0.1
Summary: Paylands API client
Home-page: https://github.com/menudoproblema/paylands
Author: Granada Dynamics, SL
License: MIT License
Platform: UNKNOWN
Classifier: Programming Language :: Python :: 3
Classifier: License :: OSI Approved :: MIT License
Classifier: Operating System :: OS Independent
Requires-Python: >=3.6
Requires-Dist: requests (==2.23.0)
